checkey-sklearn/__init__.py
checkey-sklearn/improving_naive_bayes.py
checkey-sklearn/topsis.py
chlearn/__init__.py
chlearn/improving_naive_bayes.py
chlearn/topsis.py
checkey_sklearn-0.1.1.dist-info/LICENSE.txt
checkey_sklearn-0.1.1.dist-info/METADATA
checkey_sklearn-0.1.1.dist-info/WHEEL
checkey_sklearn-0.1.1.dist-info/top_level.txt
checkey_sklearn-0.1.1.dist-info/RECORD
